codetoprompt/__init__.py
codetoprompt/analysis.py
codetoprompt/arg_parser.py
codetoprompt/cli.py
codetoprompt/config.py
codetoprompt/core.py
codetoprompt/interactive.py
codetoprompt/remote.py
codetoprompt/snapshot.py
codetoprompt/utils.py
codetoprompt/version.py
codetoprompt/compressor/__init__.py
codetoprompt/compressor/compressor.py
codetoprompt/compressor/analysers/__init__.py
codetoprompt/compressor/analysers/base.py
codetoprompt/compressor/analysers/cpp.py
codetoprompt/compressor/analysers/factory.py
codetoprompt/compressor/analysers/java.py
codetoprompt/compressor/analysers/javascript.py
codetoprompt/compressor/analysers/python.py
codetoprompt/compressor/analysers/rust.py
codetoprompt/compressor/formatters/__init__.py
codetoprompt/compressor/formatters/base.py
codetoprompt/compressor/formatters/cpp.py
codetoprompt/compressor/formatters/factory.py
codetoprompt/compressor/formatters/java.py
codetoprompt/compressor/formatters/javascript.py
codetoprompt/compressor/formatters/python.py
codetoprompt/compressor/formatters/rust.py
codetoprompt/compressor/formatters/utils.py
codetoprompt-0.7.2.dist-info/licenses/LICENSE
codetoprompt-0.7.2.dist-info/METADATA
codetoprompt-0.7.2.dist-info/WHEEL
codetoprompt-0.7.2.dist-info/entry_points.txt
codetoprompt-0.7.2.dist-info/top_level.txt
codetoprompt-0.7.2.dist-info/RECORD
