Metadata-Version: 2.4
Name: codetoprompt
Version: 0.7.2
Summary: Convert your codebase into a single LLM prompt
Author-email: Yash Bhaskar <yash9439@gmail.com>
License: MIT
Project-URL: Homepage, https://github.com/yash9439/codetoprompt
Project-URL: Documentation, https://github.com/yash9439/codetoprompt#readme
Project-URL: Repository, https://github.com/yash9439/codetoprompt
Project-URL: Issues, https://github.com/yash9439/codetoprompt/issues
Project-URL: Changelog, https://github.com/yash9439/codetoprompt/blob/main/CHANGELOG.md
Classifier: Programming Language :: Python :: 3.9
Classifier: Programming Language :: Python :: 3.10
Classifier: Programming Language :: Python :: 3.11
Classifier: Programming Language :: Python :: 3.12
Classifier: Operating System :: OS Independent
Classifier: Development Status :: 4 - Beta
Classifier: Intended Audience :: Developers
Classifier: License :: OSI Approved :: MIT License
Classifier: Topic :: Software Development :: Libraries :: Python Modules
Classifier: Topic :: Software Development :: Version Control :: Git
Classifier: Topic :: Text Processing :: General
Classifier: Topic :: Utilities
Requires-Python: >=3.9
License-File: LICENSE
Requires-Dist: tiktoken>=0.5.0
Requires-Dist: pyperclip>=1.8.2
Requires-Dist: pathspec>=0.11.0
Requires-Dist: rich>=13.0.0
Requires-Dist: toml>=0.10.2
Requires-Dist: tree-sitter-language-pack>=0.8.0
Requires-Dist: textual>=0.59.0
Requires-Dist: requests>=2.28.0
Requires-Dist: beautifulsoup4>=4.11.0
Requires-Dist: PyPDF2>=3.0.0
Requires-Dist: youtube-transcript-api>=0.6.0
Requires-Dist: nbformat>=5.9.0
Requires-Dist: nbconvert>=7.10.0
Requires-Dist: ipython
Provides-Extra: dev
Requires-Dist: pytest; extra == "dev"
Requires-Dist: pytest-cov; extra == "dev"
Requires-Dist: black; extra == "dev"
Requires-Dist: isort; extra == "dev"
Requires-Dist: mypy; extra == "dev"
Requires-Dist: flake8; extra == "dev"
Dynamic: license-file
